setup.py
guoid/__init__.py
guoid/config.py
guoid/utils.py
guoid.egg-info/PKG-INFO
guoid.egg-info/SOURCES.txt
guoid.egg-info/dependency_links.txt
guoid.egg-info/top_level.txt