Metadata-Version: 1.0
Name: guoid
Version: 0.2
Summary: Python SnowFlake Clone - Global Unique Object ID
Home-page: https://github.com/charsyam/python-guoid
Author: DaeMyung Kang
Author-email: charsyam@gmail.com
License: UNKNOWN
Platform: any
